httpself/__init__.py
httpself/cli.py
httpself/security.py
httpself/server.py
httpself-1.0.0.dist-info/entry_points.txt
httpself-1.0.0.dist-info/LICENSE
httpself-1.0.0.dist-info/WHEEL
httpself-1.0.0.dist-info/METADATA
httpself-1.0.0.dist-info/RECORD
