Metadata-Version: 2.1
Name: httpself
Version: 1.0.0
Summary: HTTP server over SSL/TLS with an automatically generated self-signed certificate
Home-page: https://github.com/bzaczynski/httpself
License: MIT
Keywords: https,server,certificate,self-signed
Author: Bartosz Zaczyński
Author-email: bartosz.zaczynski@gmail.com
Requires-Python: >=3.6,<4.0
Classifier: License :: OSI Approved :: MIT License
Classifier: Programming Language :: Python :: 3
Classifier: Programming Language :: Python :: 3.6
Classifier: Programming Language :: Python :: 3.7
Classifier: Programming Language :: Python :: 3.8
Requires-Dist: pyopenssl (>=19.1.0,<20.0.0)
Project-URL: Repository, https://github.com/bzaczynski/httpself
